eth_hub/__init__.py
eth_hub/base_key.py
eth_hub/base_key_storage.py
eth_hub/py.typed
eth_hub/signatureinfo.py
eth_hub/aws/__init__.py
eth_hub/aws/exceptions.py
eth_hub/aws/key.py
eth_hub/aws/key_store.py
eth_hub/aws/boto3_wrappers/__init__.py
eth_hub/aws/boto3_wrappers/dto.py
eth_hub/aws/boto3_wrappers/exceptions.py
eth_hub/aws/boto3_wrappers/key.py
eth_hub/aws/boto3_wrappers/metadata.py
eth_hub/aws/boto3_wrappers/signature.py
eth_hub/aws/boto3_wrappers/utils.py
eth_hub/local/__init__.py
eth_hub/local/key.py
eth_hub/local/key_storage.py
eth_hub-1.0.1.dist-info/METADATA
eth_hub-1.0.1.dist-info/WHEEL
eth_hub-1.0.1.dist-info/licenses/LICENSE
eth_hub-1.0.1.dist-info/RECORD
