Metadata-Version: 2.4
Name: eth-hub
Version: 1.0.1
Summary: Flexible Ethereum key management and signing library supporting local and external backends.
Project-URL: Homepage, https://github.com/akcelero/eth-hub
Project-URL: Repository, https://github.com/akcelero/eth-hub
Project-URL: Issues, https://github.com/akcelero/eth-hub/issues
Author-email: akcelero <akcelero@gmail.com>
License-Expression: MIT
License-File: LICENSE
Keywords: crypto,ethereum,key management,signing,vault
Classifier: Development Status :: 3 - Alpha
Classifier: Intended Audience :: Developers
Classifier: Intended Audience :: System Administrators
Classifier: License :: OSI Approved :: MIT License
Classifier: Programming Language :: Python :: 3 :: Only
Classifier: Programming Language :: Python :: 3.11
Classifier: Programming Language :: Python :: 3.12
Classifier: Programming Language :: Python :: 3.13
Classifier: Topic :: Software Development :: Libraries :: Python Modules
Requires-Python: >=3.11
Requires-Dist: asn1crypto>=1.5.1
Requires-Dist: boto3-stubs[kms]>=1.38.9
Requires-Dist: boto3>=1.38.9
Requires-Dist: botocore>=1.38.9
Requires-Dist: cryptography>=44.0.3
Requires-Dist: eth-account>=0.13.7
Requires-Dist: eth-keys>=0.7.0
Requires-Dist: mypy-boto3-kms>=1.38.0
Requires-Dist: pydantic>=2.11.4
